{
  "description": "Starter cold-boot fallback for Vagrant Story (USA) when no near-battle savestate is available. The wrapper now auto-extends timeout to cover the full plan plus slack and can leave screen-capture breadcrumbs. Latest visual checkpoints show the repeated START pulses can now reach the Vagrant Story title/logo, so this scaffold pauses menu navigation until after that title state and only then tries to open and drive the menu. Operator follow-up also confirmed that this build uses PSX-style menu mapping where X cancels and O confirms, so the menu-confirm steps now use CIRCLE instead of CROSS. The repo-local memcards still probe as blank formatted cards, so future edits should replace the save-backed Continue/Load assumption or pair the route with a populated card artifact rather than only adding more wait frames.",
  "pad_slot": 1,
  "pad_number": 1,
  "analog_mode": false,
  "initial_delay_frames": 240,
  "steps": [
    {
      "buttons": [
        "START"
      ],
      "hold_frames": 10,
      "wait_frames_after": 150,
      "note": "Skip the first intro video or title gate as soon as pad input becomes live."
    },
    {
      "buttons": [
        "START"
      ],
      "hold_frames": 10,
      "wait_frames_after": 180,
      "note": "Skip a second intro or attract-video gate if the first START only clears one clip."
    },
    {
      "buttons": [
        "START"
      ],
      "hold_frames": 10,
      "wait_frames_after": 180,
      "note": "Skip the publisher screen or the next skippable intro gate; earlier captures were still here when CROSS fired."
    },
    {
      "buttons": [
        "START"
      ],
      "hold_frames": 10,
      "wait_frames_after": 180,
      "note": "Skip the Squaresoft logo or any remaining pre-title splash."
    },
    {
      "buttons": [
        "START"
      ],
      "hold_frames": 10,
      "wait_frames_after": 180,
      "note": "Skip the opening FMV or attract clip; earlier captures suggest the run was just entering this phase."
    },
    {
      "buttons": [
        "CIRCLE"
      ],
      "hold_frames": 8,
      "wait_frames_after": 240,
      "note": "Advance from the title screen into the main menu once the intro chain has been exhausted."
    },
    {
      "buttons": [
        "START"
      ],
      "hold_frames": 8,
      "wait_frames_after": 240,
      "note": "Open the title menu after the Vagrant Story logo has settled instead of sending menu-navigation input into the logo splash."
    },
    {
      "buttons": [
        "DOWN"
      ],
      "hold_frames": 6,
      "wait_frames_after": 24,
      "note": "Move the highlight toward Continue or Load if the default cursor is elsewhere."
    },
    {
      "buttons": [
        "CIRCLE"
      ],
      "hold_frames": 8,
      "wait_frames_after": 180,
      "note": "Confirm the highlighted main-menu action."
    },
    {
      "buttons": [
        "CIRCLE"
      ],
      "hold_frames": 8,
      "wait_frames_after": 480,
      "note": "Clear the next prompt and give the game time to finish loading."
    }
  ]
}
